__init__.py
constants.py
models.py
polling_manager.py
promptforge.py
prompt_forge_sdk-0.0.1.dist-info/LICENCE.md
prompt_forge_sdk-0.0.1.dist-info/METADATA
prompt_forge_sdk-0.0.1.dist-info/WHEEL
prompt_forge_sdk-0.0.1.dist-info/top_level.txt
prompt_forge_sdk-0.0.1.dist-info/RECORD
